{"sections":[{"subsections":[{"IsEmptyTitle":true,"rules":[{"decisionSubnavigations":[],"itemId":"14606","ruleSubnavigations":[],"section":"Introduction","text":"Introduction","title":""},{"decisionSubnavigations":[],"itemId":"14607","ruleSubnavigations":[],"section":"Field Procedures","text":"Field Procedures","title":""},{"decisionSubnavigations":[],"itemId":"14608","ruleSubnavigations":[],"section":"Rule 4 - Clubs","text":"Rule 4 - Clubs","title":""},{"decisionSubnavigations":[],"itemId":"14609","ruleSubnavigations":[],"section":"Appendix II - Design of Clubs","text":"Appendix II - Design of Clubs","title":""}],"title":""},{"IsEmptyTitle":true,"rules":[{"decisionSubnavigations":[],"itemId":"14617","ruleSubnavigations":[{"hash":"01","title":"General","url":"#general"},{"hash":"02","title":"Adjustability","url":"#adjust"},{"hash":"03","title":"Length","url":"#length"},{"hash":"04","title":"Alignment","url":"#align"}],"section":"Clubs","text":"Clubs","title":""}],"title":""},{"IsEmptyTitle":true,"rules":[{"decisionSubnavigations":[],"itemId":"14618","ruleSubnavigations":[{"hash":"01","title":"Straightness","url":"#straight"},{"hash":"02","title":"Bending and Twisting Properties","url":"#bend"},{"hash":"03","title":"Attachment to Clubhead","url":"#attach"}],"section":"Shafts","text":"Shafts","title":""}],"title":""},{"IsEmptyTitle":true,"rules":[{"decisionSubnavigations":[],"itemId":"14619","ruleSubnavigations":[{"hash":"01","title":"Definition","url":"#definition"},{"hash":"02","title":"Cross-Section","url":"#cross"},{"hash":"03","title":"Two Grips","url":"#twogrips"}],"section":"The Grip","text":"The Grip","title":""}],"title":""},{"IsEmptyTitle":true,"rules":[{"decisionSubnavigations":[],"itemId":"14621","ruleSubnavigations":[{"hash":"01","title":"Plain in Shape","url":"#plain"},{"hash":"02","title":"Dimensions","url":"#dimensions"},{"hash":"03","title":"Striking Faces","url":"#striking"}],"section":"Club Head","text":"Club Head","title":""}],"title":""},{"IsEmptyTitle":true,"rules":[{"decisionSubnavigations":[],"itemId":"14620","ruleSubnavigations":[{"hash":"01","title":"General","url":"#general"},{"hash":"02","title":"Impact Area Roughness and Material","url":"#roughness"},{"hash":"03","title":"Impact Area Markings","url":"#impactmarkings"},{"hash":"04","title":"Decorative Markings","url":"#decorative"},{"hash":"05","title":"Non-Metallic Club Face Markings","url":"#non"},{"hash":"06","title":"Putter Face","url":"#putterface"}],"section":"Club Face","text":"Club Face","title":""}],"title":""},{"IsEmptyTitle":false,"rules":[{"decisionSubnavigations":[],"itemId":"14610","ruleSubnavigations":[],"section":"Rule 5 - The Golf Ball","text":"Rule 5 - The Golf Ball","title":""},{"decisionSubnavigations":[],"itemId":"14611","ruleSubnavigations":[],"section":"Appendix III - The Ball","text":"Appendix III - The Ball","title":""}],"title":"Golf Balls"},{"IsEmptyTitle":false,"rules":[{"decisionSubnavigations":[],"itemId":"14612","ruleSubnavigations":[],"section":"Supplement A","text":"Supplement A","title":""},{"decisionSubnavigations":[],"itemId":"14613","ruleSubnavigations":[],"section":"Summary of Groove Measuring Procedure","text":"Summary of Groove Measuring Procedure","title":""},{"decisionSubnavigations":[],"itemId":"14614","ruleSubnavigations":[],"section":"Abbreviated Procedure for Groove Measurement","text":"Abbreviated Procedure for Groove Measurement","title":""},{"decisionSubnavigations":[],"itemId":"2147483902","ruleSubnavigations":[],"section":"2008-2009 Punch Mark Specifications","text":"2008-2009 Punch Mark Specifications","title":""},{"decisionSubnavigations":[],"itemId":"14615","ruleSubnavigations":[],"section":"Supplement B","text":"Supplement B","title":""},{"decisionSubnavigations":[],"itemId":"2147483650","ruleSubnavigations":[],"section":"Supplement C","text":"Supplement C","title":""},{"decisionSubnavigations":[],"itemId":"2147483652","ruleSubnavigations":[],"section":"Supplement D","text":"Supplement D","title":""}],"title":"Supplements"}],"title":"Sections"}]}