{"event" : {"localtime" : "7:58 a.m. PDT", "tournament" : {"name" : "OMNIGON_1 - U.S. Amateur Four-Ball Championship (256 Players)","currentround" : "1", "legends" : {"legend" : {"type" : "courses","text" : "LC-The Olympic Club - Lake Course    OC-The Olympic Club - Ocean Course"}}, "courses" : {"course" : [{"no" : "1","holes" : "18","frontpar" : "34","backpar" : "36","par" : "70","frontyards" : "3458","frontmetres" : "3162","backyards" : "3523","backmetres" : "3221","totalyards" : "6981","totalmetres" : "6383","name" : "The Olympic Club - Lake Course","shortname" : "LC","coursename" : "Lake Course", "hole" : [{"no" : "1","par" : "4","yards" : "505","metres" : "462"}, {"no" : "2","par" : "4","yards" : "425","metres" : "389"}, {"no" : "3","par" : "3","yards" : "226","metres" : "207"}, {"no" : "4","par" : "4","yards" : "438","metres" : "401"}, {"no" : "5","par" : "4","yards" : "482","metres" : "441"}, {"no" : "6","par" : "4","yards" : "458","metres" : "419"}, {"no" : "7","par" : "4","yards" : "294","metres" : "269"}, {"no" : "8","par" : "3","yards" : "181","metres" : "166"}, {"no" : "9","par" : "4","yards" : "449","metres" : "411"}, {"no" : "10","par" : "4","yards" : "424","metres" : "388"}, {"no" : "11","par" : "4","yards" : "427","metres" : "390"}, {"no" : "12","par" : "4","yards" : "451","metres" : "412"}, {"no" : "13","par" : "3","yards" : "180","metres" : "165"}, {"no" : "14","par" : "4","yards" : "417","metres" : "381"}, {"no" : "15","par" : "3","yards" : "154","metres" : "141"}, {"no" : "16","par" : "5","yards" : "622","metres" : "569"}, {"no" : "17","par" : "5","yards" : "505","metres" : "462"}, {"no" : "18","par" : "4","yards" : "343","metres" : "314"}]}, {"no" : "2","holes" : "18","frontpar" : "35","backpar" : "35","par" : "70","frontyards" : "3468","frontmetres" : "3171","backyards" : "3293","backmetres" : "3011","totalyards" : "6761","totalmetres" : "6182","name" : "The Olympic Club - Ocean Course","shortname" : "OC","coursename" : "Ocean Course", "hole" : [{"no" : "1","par" : "4","yards" : "507","metres" : "464"}, {"no" : "2","par" : "3","yards" : "192","metres" : "176"}, {"no" : "3","par" : "4","yards" : "416","metres" : "380"}, {"no" : "4","par" : "5","yards" : "561","metres" : "513"}, {"no" : "5","par" : "3","yards" : "170","metres" : "155"}, {"no" : "6","par" : "4","yards" : "357","metres" : "326"}, {"no" : "7","par" : "4","yards" : "444","metres" : "406"}, {"no" : "8","par" : "4","yards" : "421","metres" : "385"}, {"no" : "9","par" : "4","yards" : "400","metres" : "366"}, {"no" : "10","par" : "3","yards" : "171","metres" : "156"}, {"no" : "11","par" : "5","yards" : "530","metres" : "485"}, {"no" : "12","par" : "4","yards" : "385","metres" : "352"}, {"no" : "13","par" : "4","yards" : "350","metres" : "320"}, {"no" : "14","par" : "4","yards" : "350","metres" : "320"}, {"no" : "15","par" : "4","yards" : "470","metres" : "430"}, {"no" : "16","par" : "4","yards" : "401","metres" : "367"}, {"no" : "17","par" : "3","yards" : "205","metres" : "187"}, {"no" : "18","par" : "4","yards" : "431","metres" : "394"}]}]}, "coursestats" : {"coursestat" : [{"no" : "1", "roundstats" : {"round" : "1", "sidestats" : [{"side" : "front9","eagles" : "0","birdies" : "0","pars" : "18","bogeys" : "14","doublebogeys" : "4","others" : "0","avg" : "39.500","count" : "4","total" : "158"}, {"side" : "back9","eagles" : "2","birdies" : "9","pars" : "15","bogeys" : "7","doublebogeys" : "2","others" : "0","avg" : "34.000","count" : "3","total" : "102"}, {"side" : "total","eagles" : "2","birdies" : "9","pars" : "33","bogeys" : "21","doublebogeys" : "6","others" : "0","avg" : "73.333","count" : "3","total" : "220"}], "holestats" : [{"hole" : "3","holepar" : "3","total" : "18","count" : "4","rank" : "1","avg" : "4.500","avgtopar" : "1.500","birdies" : "0","eagles" : "0","pars" : "0","bogeys" : "2","doublebogeys" : "2","others" : "0"}, {"hole" : "8","holepar" : "3","total" : "18","count" : "4","rank" : "2","avg" : "4.500","avgtopar" : "1.500","birdies" : "0","eagles" : "0","pars" : "0","bogeys" : "2","doublebogeys" : "2","others" : "0"}, {"hole" : "13","holepar" : "3","total" : "16","count" : "4","rank" : "3","avg" : "4.000","avgtopar" : "1.000","birdies" : "0","eagles" : "0","pars" : "1","bogeys" : "2","doublebogeys" : "1","others" : "0"}, {"hole" : "15","holepar" : "3","total" : "16","count" : "4","rank" : "4","avg" : "4.000","avgtopar" : "1.000","birdies" : "0","eagles" : "0","pars" : "1","bogeys" : "2","doublebogeys" : "1","others" : "0"}, {"hole" : "2","holepar" : "4","total" : "19","count" : "4","rank" : "5","avg" : "4.750","avgtopar" : "0.750","birdies" : "0","eagles" : "0","pars" : "1","bogeys" : "3","doublebogeys" : "0","others" : "0"}, {"hole" : "4","holepar" : "4","total" : "18","count" : "4","rank" : "6","avg" : "4.500","avgtopar" : "0.500","birdies" : "0","eagles" : "0","pars" : "2","bogeys" : "2","doublebogeys" : "0","others" : "0"}, {"hole" : "7","holepar" : "4","total" : "18","count" : "4","rank" : "7","avg" : "4.500","avgtopar" : "0.500","birdies" : "0","eagles" : "0","pars" : "2","bogeys" : "2","doublebogeys" : "0","others" : "0"}, {"hole" : "9","holepar" : "4","total" : "18","count" : "4","rank" : "8","avg" : "4.500","avgtopar" : "0.500","birdies" : "0","eagles" : "0","pars" : "2","bogeys" : "2","doublebogeys" : "0","others" : "0"}, {"hole" : "6","holepar" : "4","total" : "17","count" : "4","rank" : "9","avg" : "4.250","avgtopar" : "0.250","birdies" : "0","eagles" : "0","pars" : "3","bogeys" : "1","doublebogeys" : "0","others" : "0"}, {"hole" : "1","holepar" : "4","total" : "16","count" : "4","rank" : "10","avg" : "4.000","avgtopar" : "0.000","birdies" : "0","eagles" : "0","pars" : "4","bogeys" : "0","doublebogeys" : "0","others" : "0"}, {"hole" : "5","holepar" : "4","total" : "16","count" : "4","rank" : "11","avg" : "4.000","avgtopar" : "0.000","birdies" : "0","eagles" : "0","pars" : "4","bogeys" : "0","doublebogeys" : "0","others" : "0"}, {"hole" : "12","holepar" : "4","total" : "16","count" : "4","rank" : "12","avg" : "4.000","avgtopar" : "0.000","birdies" : "1","eagles" : "0","pars" : "2","bogeys" : "1","doublebogeys" : "0","others" : "0"}, {"hole" : "14","holepar" : "4","total" : "16","count" : "4","rank" : "13","avg" : "4.000","avgtopar" : "0.000","birdies" : "1","eagles" : "0","pars" : "2","bogeys" : "1","doublebogeys" : "0","others" : "0"}, {"hole" : "18","holepar" : "4","total" : "16","count" : "4","rank" : "14","avg" : "4.000","avgtopar" : "0.000","birdies" : "1","eagles" : "0","pars" : "2","bogeys" : "1","doublebogeys" : "0","others" : "0"}, {"hole" : "10","holepar" : "4","total" : "15","count" : "4","rank" : "15","avg" : "3.750","avgtopar" : "-0.250","birdies" : "1","eagles" : "0","pars" : "3","bogeys" : "0","doublebogeys" : "0","others" : "0"}, {"hole" : "11","holepar" : "4","total" : "15","count" : "4","rank" : "16","avg" : "3.750","avgtopar" : "-0.250","birdies" : "1","eagles" : "0","pars" : "3","bogeys" : "0","doublebogeys" : "0","others" : "0"}, {"hole" : "17","holepar" : "5","total" : "16","count" : "4","rank" : "17","avg" : "4.000","avgtopar" : "-1.000","birdies" : "2","eagles" : "1","pars" : "1","bogeys" : "0","doublebogeys" : "0","others" : "0"}, {"hole" : "16","holepar" : "5","total" : "11","count" : "4","rank" : "18","avg" : "3.667","avgtopar" : "-1.333","birdies" : "2","eagles" : "1","pars" : "0","bogeys" : "0","doublebogeys" : "0","others" : "0"}]}}, {"no" : "2", "roundstats" : {"round" : "1", "sidestats" : [{"side" : "front9","eagles" : "0","birdies" : "0","pars" : "0","bogeys" : "0","doublebogeys" : "0","others" : "0","avg" : "0","count" : "0","total" : "0"}, {"side" : "back9","eagles" : "0","birdies" : "0","pars" : "0","bogeys" : "0","doublebogeys" : "0","others" : "0","avg" : "0","count" : "0","total" : "0"}, {"side" : "total","eagles" : "0","birdies" : "0","pars" : "0","bogeys" : "0","doublebogeys" : "0","others" : "0","avg" : "0","count" : "0","total" : "0"}]}}]}}}}